jupyterchatz/__init__.py
jupyterchatz/_version.py
jupyterchatz/install.py
jupyterchatz-0.1.17.data/data/share/jupyter/labextensions/jupyterchatz/install.json
jupyterchatz-0.1.17.data/data/share/jupyter/labextensions/jupyterchatz/package.json
jupyterchatz-0.1.17.data/data/share/jupyter/labextensions/jupyterchatz/static/0.3436fe6fcfe6a907fa8f.js
jupyterchatz-0.1.17.data/data/share/jupyter/labextensions/jupyterchatz/static/581.5bfc09a53a0e93cace85.js
jupyterchatz-0.1.17.data/data/share/jupyter/labextensions/jupyterchatz/static/728.d2570fadb0411407001f.js
jupyterchatz-0.1.17.data/data/share/jupyter/labextensions/jupyterchatz/static/remoteEntry.8c121726581778aacfad.js
jupyterchatz-0.1.17.data/data/share/jupyter/labextensions/jupyterchatz/static/style.js
jupyterchatz-0.1.17.data/data/share/jupyter/labextensions/jupyterchatz/static/third-party-licenses.json
jupyterchatz-0.1.17.dist-info/METADATA
jupyterchatz-0.1.17.dist-info/WHEEL
jupyterchatz-0.1.17.dist-info/entry_points.txt
jupyterchatz-0.1.17.dist-info/licenses/LICENSE
jupyterchatz-0.1.17.dist-info/RECORD
