Metadata-Version: 2.4
Name: jupyterchatz
Version: 0.1.17
Dynamic: Keywords
Summary: A JupyterLab extension for chat functionality with MCP (Model Context Protocol) support.
Project-URL: Homepage, https://github.com/Zhoums396/jupyterchatz
Project-URL: Bug Tracker, https://github.com/Zhoums396/jupyterchatz/issues
Project-URL: Repository, https://github.com/Zhoums396/jupyterchatz.git
Author-email: zms <18652950852@163.com>
License: BSD 3-Clause License
License-File: LICENSE
Classifier: Framework :: Jupyter
Classifier: Framework :: Jupyter :: JupyterLab
Classifier: Framework :: Jupyter :: JupyterLab :: 4
Classifier: Framework :: Jupyter :: JupyterLab :: Extensions
Classifier: Framework :: Jupyter :: JupyterLab :: Extensions :: Prebuilt
Classifier: License :: OSI Approved :: BSD License
Classifier: Programming Language :: Python
Classifier: Programming Language :: Python :: 3
Classifier: Programming Language :: Python :: 3.8
Classifier: Programming Language :: Python :: 3.9
Classifier: Programming Language :: Python :: 3.10
Classifier: Programming Language :: Python :: 3.11
Requires-Python: >=3.8
